{
  "train_no": "C6584",
  "train_type": "C",
  "depart_station": "烟台",
  "arrive_station": "青岛",
  "depart_time": "14:21",
  "arrive_time": "16:11",
  "stops": [
    {
      "seq": 1,
      "station_name": "烟台",
      "arrive_time": "14:21",
      "depart_time": "14:21",
      "stay_min": ""
    },
    {
      "seq": 2,
      "station_name": "莱阳",
      "arrive_time": "14:58",
      "depart_time": "15:01",
      "stay_min": "3"
    },
    {
      "seq": 3,
      "station_name": "夏格庄",
      "arrive_time": "15:15",
      "depart_time": "15:17",
      "stay_min": "2"
    },
    {
      "seq": 4,
      "station_name": "青岛北",
      "arrive_time": "15:43",
      "depart_time": "15:49",
      "stay_min": "6"
    },
    {
      "seq": 5,
      "station_name": "青岛",
      "arrive_time": "16:11",
      "depart_time": "",
      "stay_min": ""
    }
  ],
  "fares": {
    "price_first": 118.0,
    "price_second": 74.0,
    "price_no_seat": 74.0
  },
  "fetched_at": "2026-05-01T01:52:29.951326"
}