{
  "train_no": "C9325",
  "train_type": "C",
  "depart_station": "延安",
  "arrive_station": "西安北",
  "depart_time": "17:40",
  "arrive_time": "19:06",
  "stops": [
    {
      "seq": 1,
      "station_name": "延安",
      "arrive_time": "17:40",
      "depart_time": "17:40",
      "stay_min": ""
    },
    {
      "seq": 2,
      "station_name": "富县北",
      "arrive_time": "18:01",
      "depart_time": "18:01",
      "stay_min": ""
    },
    {
      "seq": 3,
      "station_name": "黄陵",
      "arrive_time": "18:21",
      "depart_time": "18:21",
      "stay_min": ""
    },
    {
      "seq": 4,
      "station_name": "铜川北",
      "arrive_time": "18:42",
      "depart_time": "18:42",
      "stay_min": ""
    },
    {
      "seq": 5,
      "station_name": "高陵",
      "arrive_time": "19:06",
      "depart_time": "",
      "stay_min": ""
    },
    {
      "seq": 6,
      "station_name": "西安北",
      "arrive_time": "19:06",
      "depart_time": "",
      "stay_min": ""
    }
  ],
  "fares": {
    "price_business": 757.0,
    "price_first": 346.0,
    "price_second": 216.0,
    "price_no_seat": 216.0
  },
  "fetched_at": "2026-05-01T02:45:19.887263"
}