{
  "train_no": "C9472",
  "train_type": "C",
  "depart_station": "黄龙九寨",
  "arrive_station": "双流机场",
  "depart_time": "10:42",
  "arrive_time": "12:46",
  "stops": [
    {
      "seq": 1,
      "station_name": "黄龙九寨",
      "arrive_time": "10:42",
      "depart_time": "10:42",
      "stay_min": ""
    },
    {
      "seq": 2,
      "station_name": "成都东",
      "arrive_time": "12:23",
      "depart_time": "12:30",
      "stay_min": "7"
    },
    {
      "seq": 3,
      "station_name": "双流机场",
      "arrive_time": "12:46",
      "depart_time": "",
      "stay_min": ""
    }
  ],
  "fares": {
    "price_first": 243.0,
    "price_second": 151.0,
    "price_no_seat": 151.0
  },
  "fetched_at": "2026-05-01T02:46:48.852390"
}