{
  "train_no": "D1802",
  "train_type": "D",
  "depart_station": "广州南",
  "arrive_station": "成都东",
  "depart_time": "06:36",
  "arrive_time": "15:35",
  "stops": [
    {
      "seq": 1,
      "station_name": "广州南",
      "arrive_time": "06:36",
      "depart_time": "06:36",
      "stay_min": ""
    },
    {
      "seq": 2,
      "station_name": "肇庆东",
      "arrive_time": "07:11",
      "depart_time": "07:11",
      "stay_min": ""
    },
    {
      "seq": 3,
      "station_name": "阳朔",
      "arrive_time": "08:37",
      "depart_time": "08:37",
      "stay_min": ""
    },
    {
      "seq": 4,
      "station_name": "桂林西",
      "arrive_time": "09:07",
      "depart_time": "09:07",
      "stay_min": ""
    },
    {
      "seq": 5,
      "station_name": "三江南",
      "arrive_time": "09:41",
      "depart_time": "09:41",
      "stay_min": ""
    },
    {
      "seq": 6,
      "station_name": "从江",
      "arrive_time": "10:03",
      "depart_time": "10:03",
      "stay_min": ""
    },
    {
      "seq": 7,
      "station_name": "榕江",
      "arrive_time": "10:36",
      "depart_time": "10:36",
      "stay_min": ""
    },
    {
      "seq": 8,
      "station_name": "都匀东",
      "arrive_time": "11:10",
      "depart_time": "11:10",
      "stay_min": ""
    },
    {
      "seq": 9,
      "station_name": "龙洞堡",
      "arrive_time": "11:45",
      "depart_time": "11:45",
      "stay_min": ""
    },
    {
      "seq": 10,
      "station_name": "贵阳东",
      "arrive_time": "12:00",
      "depart_time": "12:00",
      "stay_min": ""
    },
    {
      "seq": 11,
      "station_name": "黔西",
      "arrive_time": "12:33",
      "depart_time": "12:33",
      "stay_min": ""
    },
    {
      "seq": 12,
      "station_name": "毕节",
      "arrive_time": "13:13",
      "depart_time": "13:13",
      "stay_min": ""
    },
    {
      "seq": 13,
      "station_name": "宜宾西",
      "arrive_time": "14:21",
      "depart_time": "14:21",
      "stay_min": ""
    },
    {
      "seq": 14,
      "station_name": "犍为",
      "arrive_time": "14:51",
      "depart_time": "14:51",
      "stay_min": ""
    },
    {
      "seq": 15,
      "station_name": "乐山",
      "arrive_time": "15:08",
      "depart_time": "15:08",
      "stay_min": ""
    },
    {
      "seq": 16,
      "station_name": "青神",
      "arrive_time": "15:23",
      "depart_time": "15:23",
      "stay_min": ""
    },
    {
      "seq": 17,
      "station_name": "眉山东",
      "arrive_time": "15:35",
      "depart_time": "",
      "stay_min": ""
    },
    {
      "seq": 18,
      "station_name": "成都东",
      "arrive_time": "15:35",
      "depart_time": "",
      "stay_min": ""
    }
  ],
  "fares": {
    "price_first": 1033.0,
    "price_second": 646.0,
    "price_no_seat": 646.0
  },
  "fetched_at": "2026-05-01T03:05:13.011602"
}