{
  "train_no": "D28",
  "train_type": "D",
  "depart_station": "深圳",
  "arrive_station": "北京丰台",
  "depart_time": "14:12",
  "arrive_time": "11:04",
  "stops": [
    {
      "seq": 1,
      "station_name": "深圳",
      "arrive_time": "14:12",
      "depart_time": "14:12",
      "stay_min": ""
    },
    {
      "seq": 2,
      "station_name": "东莞东",
      "arrive_time": "14:55",
      "depart_time": "14:55",
      "stay_min": ""
    },
    {
      "seq": 3,
      "station_name": "惠州",
      "arrive_time": "15:39",
      "depart_time": "15:39",
      "stay_min": ""
    },
    {
      "seq": 4,
      "station_name": "赣州",
      "arrive_time": "19:59",
      "depart_time": "19:59",
      "stay_min": ""
    },
    {
      "seq": 5,
      "station_name": "吉安",
      "arrive_time": "21:50",
      "depart_time": "21:50",
      "stay_min": ""
    },
    {
      "seq": 6,
      "station_name": "南昌",
      "arrive_time": "00:16",
      "depart_time": "00:16",
      "stay_min": ""
    },
    {
      "seq": 7,
      "station_name": "阜阳",
      "arrive_time": "05:16",
      "depart_time": "05:16",
      "stay_min": ""
    },
    {
      "seq": 8,
      "station_name": "菏泽",
      "arrive_time": "07:31",
      "depart_time": "07:31",
      "stay_min": ""
    },
    {
      "seq": 9,
      "station_name": "聊城",
      "arrive_time": "08:40",
      "depart_time": "08:40",
      "stay_min": ""
    },
    {
      "seq": 10,
      "station_name": "衡水",
      "arrive_time": "10:04",
      "depart_time": "10:04",
      "stay_min": ""
    },
    {
      "seq": 11,
      "station_name": "任丘",
      "arrive_time": "11:04",
      "depart_time": "",
      "stay_min": ""
    },
    {
      "seq": 12,
      "station_name": "北京丰台",
      "arrive_time": "11:04",
      "depart_time": "",
      "stay_min": ""
    }
  ],
  "fares": {
    "price_second": 556.0,
    "price_no_seat": 556.0
  },
  "fetched_at": "2026-05-01T03:23:29.865275"
}