{
  "train_no": "D5110",
  "train_type": "D",
  "depart_station": "青城山",
  "arrive_station": "重庆北",
  "depart_time": "15:19",
  "arrive_time": "19:28",
  "stops": [
    {
      "seq": 1,
      "station_name": "青城山",
      "arrive_time": "15:19",
      "depart_time": "15:19",
      "stay_min": ""
    },
    {
      "seq": 2,
      "station_name": "都江堰",
      "arrive_time": "15:26",
      "depart_time": "15:28",
      "stay_min": "2"
    },
    {
      "seq": 3,
      "station_name": "安靖",
      "arrive_time": "15:52",
      "depart_time": "16:10",
      "stay_min": "18"
    },
    {
      "seq": 4,
      "station_name": "成都西",
      "arrive_time": "16:20",
      "depart_time": "16:24",
      "stay_min": "4"
    },
    {
      "seq": 5,
      "station_name": "成都南",
      "arrive_time": "16:36",
      "depart_time": "16:40",
      "stay_min": "4"
    },
    {
      "seq": 6,
      "station_name": "成都东",
      "arrive_time": "16:50",
      "depart_time": "16:58",
      "stay_min": "8"
    },
    {
      "seq": 7,
      "station_name": "遂宁",
      "arrive_time": "17:55",
      "depart_time": "18:07",
      "stay_min": "12"
    },
    {
      "seq": 8,
      "station_name": "潼南",
      "arrive_time": "18:33",
      "depart_time": "18:37",
      "stay_min": "4"
    },
    {
      "seq": 9,
      "station_name": "合川",
      "arrive_time": "19:01",
      "depart_time": "19:03",
      "stay_min": "2"
    },
    {
      "seq": 10,
      "station_name": "重庆北",
      "arrive_time": "19:28",
      "depart_time": "",
      "stay_min": ""
    }
  ],
  "fares": {
    "price_first": 223.0,
    "price_second": 145.0,
    "price_no_seat": 145.0
  },
  "fetched_at": "2026-05-01T04:00:37.336726"
}