{
  "train_no": "D6985",
  "train_type": "D",
  "depart_station": "哈尔滨",
  "arrive_station": "齐齐哈尔南",
  "depart_time": "07:40",
  "arrive_time": "09:02",
  "stops": [
    {
      "seq": 1,
      "station_name": "哈尔滨",
      "arrive_time": "07:40",
      "depart_time": "07:40",
      "stay_min": ""
    },
    {
      "seq": 2,
      "station_name": "哈尔滨北",
      "arrive_time": "07:52",
      "depart_time": "07:52",
      "stay_min": ""
    },
    {
      "seq": 3,
      "station_name": "肇东",
      "arrive_time": "08:10",
      "depart_time": "08:10",
      "stay_min": ""
    },
    {
      "seq": 4,
      "station_name": "大庆东",
      "arrive_time": "08:39",
      "depart_time": "08:39",
      "stay_min": ""
    },
    {
      "seq": 5,
      "station_name": "杜尔伯特",
      "arrive_time": "09:02",
      "depart_time": "",
      "stay_min": ""
    },
    {
      "seq": 6,
      "station_name": "齐齐哈尔南",
      "arrive_time": "09:02",
      "depart_time": "",
      "stay_min": ""
    }
  ],
  "fares": {
    "price_first": 157.0,
    "price_second": 98.0,
    "price_no_seat": 98.0
  },
  "fetched_at": "2026-05-01T04:32:10.312488"
}