{
  "train_no": "D7019",
  "train_type": "D",
  "depart_station": "武汉",
  "arrive_station": "武穴北",
  "depart_time": "07:06",
  "arrive_time": "08:19",
  "stops": [
    {
      "seq": 1,
      "station_name": "武汉",
      "arrive_time": "07:06",
      "depart_time": "07:06",
      "stay_min": ""
    },
    {
      "seq": 2,
      "station_name": "黄冈西",
      "arrive_time": "07:36",
      "depart_time": "07:36",
      "stay_min": ""
    },
    {
      "seq": 3,
      "station_name": "黄冈东",
      "arrive_time": "07:48",
      "depart_time": "07:48",
      "stay_min": ""
    },
    {
      "seq": 4,
      "station_name": "浠水南",
      "arrive_time": "08:04",
      "depart_time": "08:04",
      "stay_min": ""
    },
    {
      "seq": 5,
      "station_name": "蕲春南",
      "arrive_time": "08:19",
      "depart_time": "",
      "stay_min": ""
    },
    {
      "seq": 6,
      "station_name": "武穴北",
      "arrive_time": "08:19",
      "depart_time": "",
      "stay_min": ""
    }
  ],
  "fares": {
    "price_first": 120.0,
    "price_second": 75.0,
    "price_no_seat": 75.0
  },
  "fetched_at": "2026-05-01T04:32:31.758448"
}