{
  "train_no": "D9385",
  "train_type": "D",
  "depart_station": "西安北",
  "arrive_station": "宝鸡南",
  "depart_time": "15:14",
  "arrive_time": "16:02",
  "stops": [
    {
      "seq": 1,
      "station_name": "西安北",
      "arrive_time": "15:14",
      "depart_time": "15:14",
      "stay_min": ""
    },
    {
      "seq": 2,
      "station_name": "杨陵南",
      "arrive_time": "15:45",
      "depart_time": "15:45",
      "stay_min": ""
    },
    {
      "seq": 3,
      "station_name": "岐山",
      "arrive_time": "16:02",
      "depart_time": "",
      "stay_min": ""
    },
    {
      "seq": 4,
      "station_name": "宝鸡南",
      "arrive_time": "16:02",
      "depart_time": "",
      "stay_min": ""
    }
  ],
  "fares": {
    "price_business": 154.5,
    "price_first": 82.5,
    "price_second": 51.5,
    "price_no_seat": 51.5
  },
  "fetched_at": "2026-05-01T05:14:37.751289"
}