{
  "train_no": "G2103",
  "train_type": "G",
  "depart_station": "威海",
  "arrive_station": "信阳东",
  "depart_time": "12:22",
  "arrive_time": "21:38",
  "stops": [
    {
      "seq": 1,
      "station_name": "威海",
      "arrive_time": "12:22",
      "depart_time": "12:22",
      "stay_min": ""
    },
    {
      "seq": 2,
      "station_name": "文登东",
      "arrive_time": "12:33",
      "depart_time": "12:35",
      "stay_min": "2"
    },
    {
      "seq": 3,
      "station_name": "荣成",
      "arrive_time": "12:46",
      "depart_time": "12:48",
      "stay_min": "2"
    },
    {
      "seq": 4,
      "station_name": "文登南",
      "arrive_time": "13:01",
      "depart_time": "13:03",
      "stay_min": "2"
    },
    {
      "seq": 5,
      "station_name": "乳山南",
      "arrive_time": "13:20",
      "depart_time": "13:22",
      "stay_min": "2"
    },
    {
      "seq": 6,
      "station_name": "莱阳南",
      "arrive_time": "13:43",
      "depart_time": "13:45",
      "stay_min": "2"
    },
    {
      "seq": 7,
      "station_name": "莱西",
      "arrive_time": "14:01",
      "depart_time": "14:03",
      "stay_min": "2"
    },
    {
      "seq": 8,
      "station_name": "青州市",
      "arrive_time": "15:27",
      "depart_time": "15:29",
      "stay_min": "2"
    },
    {
      "seq": 9,
      "station_name": "淄博",
      "arrive_time": "15:48",
      "depart_time": "15:51",
      "stay_min": "3"
    },
    {
      "seq": 10,
      "station_name": "济南",
      "arrive_time": "16:38",
      "depart_time": "16:45",
      "stay_min": "7"
    },
    {
      "seq": 11,
      "station_name": "曲阜东",
      "arrive_time": "17:23",
      "depart_time": "17:25",
      "stay_min": "2"
    },
    {
      "seq": 12,
      "station_name": "济宁北",
      "arrive_time": "17:47",
      "depart_time": "17:49",
      "stay_min": "2"
    },
    {
      "seq": 13,
      "station_name": "巨野北",
      "arrive_time": "18:05",
      "depart_time": "18:07",
      "stay_min": "2"
    },
    {
      "seq": 14,
      "station_name": "菏泽东",
      "arrive_time": "18:24",
      "depart_time": "18:26",
      "stay_min": "2"
    },
    {
      "seq": 15,
      "station_name": "庄寨",
      "arrive_time": "18:39",
      "depart_time": "18:51",
      "stay_min": "12"
    },
    {
      "seq": 16,
      "station_name": "郑州东",
      "arrive_time": "19:38",
      "depart_time": "19:56",
      "stay_min": "18"
    },
    {
      "seq": 17,
      "station_name": "许昌东",
      "arrive_time": "20:18",
      "depart_time": "20:27",
      "stay_min": "9"
    },
    {
      "seq": 18,
      "station_name": "漯河西",
      "arrive_time": "20:46",
      "depart_time": "20:52",
      "stay_min": "6"
    },
    {
      "seq": 19,
      "station_name": "驻马店西",
      "arrive_time": "21:10",
      "depart_time": "21:12",
      "stay_min": "2"
    },
    {
      "seq": 20,
      "station_name": "信阳东",
      "arrive_time": "21:38",
      "depart_time": "",
      "stay_min": ""
    }
  ],
  "fares": {
    "price_business": 2553.0,
    "price_first": 1167.0,
    "price_second": 730.0,
    "price_no_seat": 730.0
  },
  "fetched_at": "2026-05-01T06:01:52.694912"
}