{
  "train_no": "G3739",
  "train_type": "G",
  "depart_station": "西安北",
  "arrive_station": "南宁东",
  "depart_time": "08:07",
  "arrive_time": "20:26",
  "stops": [
    {
      "seq": 1,
      "station_name": "西安北",
      "arrive_time": "08:07",
      "depart_time": "08:07",
      "stay_min": ""
    },
    {
      "seq": 2,
      "station_name": "鄠邑",
      "arrive_time": "08:26",
      "depart_time": "08:26",
      "stay_min": ""
    },
    {
      "seq": 3,
      "station_name": "洋县西",
      "arrive_time": "09:12",
      "depart_time": "09:12",
      "stay_min": ""
    },
    {
      "seq": 4,
      "station_name": "汉中",
      "arrive_time": "09:33",
      "depart_time": "09:33",
      "stay_min": ""
    },
    {
      "seq": 5,
      "station_name": "广元",
      "arrive_time": "10:21",
      "depart_time": "10:21",
      "stay_min": ""
    },
    {
      "seq": 6,
      "station_name": "德阳",
      "arrive_time": "11:28",
      "depart_time": "11:28",
      "stay_min": ""
    },
    {
      "seq": 7,
      "station_name": "成都东",
      "arrive_time": "11:59",
      "depart_time": "11:59",
      "stay_min": ""
    },
    {
      "seq": 8,
      "station_name": "简阳南",
      "arrive_time": "12:25",
      "depart_time": "12:25",
      "stay_min": ""
    },
    {
      "seq": 9,
      "station_name": "资阳北",
      "arrive_time": "12:44",
      "depart_time": "12:44",
      "stay_min": ""
    },
    {
      "seq": 10,
      "station_name": "重庆西",
      "arrive_time": "13:46",
      "depart_time": "13:46",
      "stay_min": ""
    },
    {
      "seq": 11,
      "station_name": "遵义",
      "arrive_time": "15:06",
      "depart_time": "15:06",
      "stay_min": ""
    },
    {
      "seq": 12,
      "station_name": "息烽",
      "arrive_time": "15:35",
      "depart_time": "15:35",
      "stay_min": ""
    },
    {
      "seq": 13,
      "station_name": "贵阳东",
      "arrive_time": "16:04",
      "depart_time": "16:04",
      "stay_min": ""
    },
    {
      "seq": 14,
      "station_name": "都匀东",
      "arrive_time": "16:41",
      "depart_time": "16:41",
      "stay_min": ""
    },
    {
      "seq": 15,
      "station_name": "三都县",
      "arrive_time": "16:54",
      "depart_time": "16:54",
      "stay_min": ""
    },
    {
      "seq": 16,
      "station_name": "桂林北",
      "arrive_time": "18:13",
      "depart_time": "18:13",
      "stay_min": ""
    },
    {
      "seq": 17,
      "station_name": "桂林",
      "arrive_time": "18:28",
      "depart_time": "18:28",
      "stay_min": ""
    },
    {
      "seq": 18,
      "station_name": "柳州",
      "arrive_time": "19:33",
      "depart_time": "19:33",
      "stay_min": ""
    },
    {
      "seq": 19,
      "station_name": "来宾北",
      "arrive_time": "20:00",
      "depart_time": "20:00",
      "stay_min": ""
    },
    {
      "seq": 20,
      "station_name": "宾阳",
      "arrive_time": "20:26",
      "depart_time": "",
      "stay_min": ""
    },
    {
      "seq": 21,
      "station_name": "南宁东",
      "arrive_time": "20:26",
      "depart_time": "",
      "stay_min": ""
    }
  ],
  "fares": {
    "price_business": 3377.0,
    "price_first": 1588.0,
    "price_second": 992.5,
    "price_no_seat": 992.5
  },
  "fetched_at": "2026-05-01T06:46:08.223528"
}