{
  "train_no": "G7510",
  "train_type": "G",
  "depart_station": "宁波",
  "arrive_station": "上海南",
  "depart_time": "11:20",
  "arrive_time": "12:36",
  "stops": [
    {
      "seq": 1,
      "station_name": "宁波",
      "arrive_time": "11:20",
      "depart_time": "11:20",
      "stay_min": ""
    },
    {
      "seq": 2,
      "station_name": "绍兴北",
      "arrive_time": "11:55",
      "depart_time": "11:55",
      "stay_min": ""
    },
    {
      "seq": 3,
      "station_name": "杭州东",
      "arrive_time": "12:17",
      "depart_time": "12:17",
      "stay_min": ""
    },
    {
      "seq": 4,
      "station_name": "桐乡",
      "arrive_time": "12:36",
      "depart_time": "",
      "stay_min": ""
    },
    {
      "seq": 5,
      "station_name": "上海南",
      "arrive_time": "12:36",
      "depart_time": "",
      "stay_min": ""
    }
  ],
  "fares": {
    "price_first": 274.0,
    "price_second": 171.0,
    "price_no_seat": 171.0
  },
  "fetched_at": "2026-05-01T08:29:15.107998"
}