{
  "train_no": "G9831",
  "train_type": "G",
  "depart_station": "福州南",
  "arrive_station": "厦门",
  "depart_time": "08:28",
  "arrive_time": "09:34",
  "stops": [
    {
      "seq": 1,
      "station_name": "福州南",
      "arrive_time": "08:28",
      "depart_time": "08:28",
      "stay_min": ""
    },
    {
      "seq": 2,
      "station_name": "泉州南",
      "arrive_time": "09:13",
      "depart_time": "09:13",
      "stay_min": ""
    },
    {
      "seq": 3,
      "station_name": "厦门北",
      "arrive_time": "09:34",
      "depart_time": "",
      "stay_min": ""
    },
    {
      "seq": 4,
      "station_name": "厦门",
      "arrive_time": "09:34",
      "depart_time": "",
      "stay_min": ""
    }
  ],
  "fares": {
    "price_business": 489.0,
    "price_first": 224.0,
    "price_second": 140.0,
    "price_no_seat": 140.0
  },
  "fetched_at": "2026-05-01T09:25:36.337055"
}