{
  "train_no": "K1517",
  "train_type": "K",
  "depart_station": "沈阳",
  "arrive_station": "西宁",
  "depart_time": "15:27",
  "arrive_time": "08:21",
  "stops": [
    {
      "seq": 1,
      "station_name": "沈阳",
      "arrive_time": "15:27",
      "depart_time": "15:27",
      "stay_min": ""
    },
    {
      "seq": 2,
      "station_name": "泡子",
      "arrive_time": "17:12",
      "depart_time": "17:15",
      "stay_min": "3"
    },
    {
      "seq": 3,
      "station_name": "彰武",
      "arrive_time": "17:36",
      "depart_time": "17:39",
      "stay_min": "3"
    },
    {
      "seq": 4,
      "station_name": "甘旗卡",
      "arrive_time": "18:29",
      "depart_time": "18:32",
      "stay_min": "3"
    },
    {
      "seq": 5,
      "station_name": "通辽",
      "arrive_time": "19:31",
      "depart_time": "20:01",
      "stay_min": "30"
    },
    {
      "seq": 6,
      "station_name": "开鲁",
      "arrive_time": "21:03",
      "depart_time": "21:06",
      "stay_min": "3"
    },
    {
      "seq": 7,
      "station_name": "查布嘎",
      "arrive_time": "22:16",
      "depart_time": "22:19",
      "stay_min": "3"
    },
    {
      "seq": 8,
      "station_name": "林东",
      "arrive_time": "23:00",
      "depart_time": "23:03",
      "stay_min": "3"
    },
    {
      "seq": 9,
      "station_name": "大板",
      "arrive_time": "00:08",
      "depart_time": "00:16",
      "stay_min": "8"
    },
    {
      "seq": 10,
      "station_name": "林西",
      "arrive_time": "00:54",
      "depart_time": "00:57",
      "stay_min": "3"
    },
    {
      "seq": 11,
      "station_name": "桑根达来",
      "arrive_time": "03:17",
      "depart_time": "03:23",
      "stay_min": "6"
    },
    {
      "seq": 12,
      "station_name": "正镶白旗",
      "arrive_time": "04:23",
      "depart_time": "04:29",
      "stay_min": "6"
    },
    {
      "seq": 13,
      "station_name": "商都",
      "arrive_time": "06:11",
      "depart_time": "06:14",
      "stay_min": "3"
    },
    {
      "seq": 14,
      "station_name": "集宁南",
      "arrive_time": "07:30",
      "depart_time": "07:56",
      "stay_min": "26"
    },
    {
      "seq": 15,
      "station_name": "呼和浩特东",
      "arrive_time": "09:18",
      "depart_time": "09:43",
      "stay_min": "25"
    },
    {
      "seq": 16,
      "station_name": "萨拉齐",
      "arrive_time": "10:56",
      "depart_time": "11:21",
      "stay_min": "25"
    },
    {
      "seq": 17,
      "station_name": "包头东",
      "arrive_time": "11:51",
      "depart_time": "12:01",
      "stay_min": "10"
    },
    {
      "seq": 18,
      "station_name": "包头",
      "arrive_time": "12:16",
      "depart_time": "12:28",
      "stay_min": "12"
    },
    {
      "seq": 19,
      "station_name": "乌拉山西",
      "arrive_time": "13:37",
      "depart_time": "13:42",
      "stay_min": "5"
    },
    {
      "seq": 20,
      "station_name": "刘召",
      "arrive_time": "14:18",
      "depart_time": "14:23",
      "stay_min": "5"
    },
    {
      "seq": 21,
      "station_name": "巴彦淖尔",
      "arrive_time": "15:04",
      "depart_time": "15:12",
      "stay_min": "8"
    },
    {
      "seq": 22,
      "station_name": "巴彦高勒",
      "arrive_time": "15:56",
      "depart_time": "16:00",
      "stay_min": "4"
    },
    {
      "seq": 23,
      "station_name": "乌海",
      "arrive_time": "16:52",
      "depart_time": "17:02",
      "stay_min": "10"
    },
    {
      "seq": 24,
      "station_name": "乌海西",
      "arrive_time": "17:33",
      "depart_time": "17:41",
      "stay_min": "8"
    },
    {
      "seq": 25,
      "station_name": "石嘴山南",
      "arrive_time": "18:45",
      "depart_time": "18:55",
      "stay_min": "10"
    },
    {
      "seq": 26,
      "station_name": "银川",
      "arrive_time": "19:37",
      "depart_time": "19:52",
      "stay_min": "15"
    },
    {
      "seq": 27,
      "station_name": "青铜峡",
      "arrive_time": "20:46",
      "depart_time": "20:51",
      "stay_min": "5"
    },
    {
      "seq": 28,
      "station_name": "中宁",
      "arrive_time": "21:47",
      "depart_time": "21:53",
      "stay_min": "6"
    },
    {
      "seq": 29,
      "station_name": "中卫",
      "arrive_time": "22:49",
      "depart_time": "23:04",
      "stay_min": "15"
    },
    {
      "seq": 30,
      "station_name": "兰州",
      "arrive_time": "05:04",
      "depart_time": "05:27",
      "stay_min": "23"
    },
    {
      "seq": 31,
      "station_name": "西宁",
      "arrive_time": "08:21",
      "depart_time": "",
      "stay_min": ""
    }
  ],
  "fares": {
    "price_hard_seat": 290.5
  },
  "fetched_at": "2026-05-01T09:36:29.002079"
}