{
  "train_no": "K4033",
  "train_type": "K",
  "depart_station": "阜阳",
  "arrive_station": "东莞东",
  "depart_time": "13:40",
  "arrive_time": "19:21",
  "stops": [
    {
      "seq": 1,
      "station_name": "阜阳",
      "arrive_time": "13:40",
      "depart_time": "13:40",
      "stay_min": ""
    },
    {
      "seq": 2,
      "station_name": "潢川",
      "arrive_time": "15:06",
      "depart_time": "15:06",
      "stay_min": ""
    },
    {
      "seq": 3,
      "station_name": "光山",
      "arrive_time": "15:27",
      "depart_time": "15:27",
      "stay_min": ""
    },
    {
      "seq": 4,
      "station_name": "麻城",
      "arrive_time": "16:38",
      "depart_time": "16:38",
      "stay_min": ""
    },
    {
      "seq": 5,
      "station_name": "黄州",
      "arrive_time": "17:23",
      "depart_time": "17:23",
      "stay_min": ""
    },
    {
      "seq": 6,
      "station_name": "蕲春",
      "arrive_time": "18:09",
      "depart_time": "18:09",
      "stay_min": ""
    },
    {
      "seq": 7,
      "station_name": "九江",
      "arrive_time": "19:21",
      "depart_time": "",
      "stay_min": ""
    },
    {
      "seq": 8,
      "station_name": "东莞东",
      "arrive_time": "19:21",
      "depart_time": "",
      "stay_min": ""
    }
  ],
  "fares": {},
  "fetched_at": "2026-05-01T09:45:53.944377"
}