{
  "train_no": "K4836",
  "train_type": "K",
  "depart_station": "牡丹江",
  "arrive_station": "大连",
  "depart_time": "16:38",
  "arrive_time": "10:14",
  "stops": [
    {
      "seq": 1,
      "station_name": "牡丹江",
      "arrive_time": "16:38",
      "depart_time": "16:38",
      "stay_min": ""
    },
    {
      "seq": 2,
      "station_name": "横道河子",
      "arrive_time": "17:52",
      "depart_time": "17:52",
      "stay_min": ""
    },
    {
      "seq": 3,
      "station_name": "亚布力",
      "arrive_time": "19:02",
      "depart_time": "19:02",
      "stay_min": ""
    },
    {
      "seq": 4,
      "station_name": "尚志",
      "arrive_time": "20:01",
      "depart_time": "20:01",
      "stay_min": ""
    },
    {
      "seq": 5,
      "station_name": "玉泉",
      "arrive_time": "21:06",
      "depart_time": "21:06",
      "stay_min": ""
    },
    {
      "seq": 6,
      "station_name": "阿城",
      "arrive_time": "21:30",
      "depart_time": "21:30",
      "stay_min": ""
    },
    {
      "seq": 7,
      "station_name": "哈尔滨东",
      "arrive_time": "22:22",
      "depart_time": "22:22",
      "stay_min": ""
    },
    {
      "seq": 8,
      "station_name": "哈尔滨",
      "arrive_time": "23:04",
      "depart_time": "23:04",
      "stay_min": ""
    },
    {
      "seq": 9,
      "station_name": "长春",
      "arrive_time": "01:51",
      "depart_time": "01:51",
      "stay_min": ""
    },
    {
      "seq": 10,
      "station_name": "沈阳",
      "arrive_time": "05:27",
      "depart_time": "05:27",
      "stay_min": ""
    },
    {
      "seq": 11,
      "station_name": "辽阳",
      "arrive_time": "06:13",
      "depart_time": "06:13",
      "stay_min": ""
    },
    {
      "seq": 12,
      "station_name": "鞍山",
      "arrive_time": "06:35",
      "depart_time": "06:35",
      "stay_min": ""
    },
    {
      "seq": 13,
      "station_name": "海城",
      "arrive_time": "07:04",
      "depart_time": "07:04",
      "stay_min": ""
    },
    {
      "seq": 14,
      "station_name": "大石桥",
      "arrive_time": "07:37",
      "depart_time": "07:37",
      "stay_min": ""
    },
    {
      "seq": 15,
      "station_name": "熊岳城",
      "arrive_time": "08:18",
      "depart_time": "08:18",
      "stay_min": ""
    },
    {
      "seq": 16,
      "station_name": "瓦房店",
      "arrive_time": "09:10",
      "depart_time": "09:10",
      "stay_min": ""
    },
    {
      "seq": 17,
      "station_name": "普兰店",
      "arrive_time": "09:34",
      "depart_time": "09:34",
      "stay_min": ""
    },
    {
      "seq": 18,
      "station_name": "金州",
      "arrive_time": "10:14",
      "depart_time": "",
      "stay_min": ""
    },
    {
      "seq": 19,
      "station_name": "大连",
      "arrive_time": "10:14",
      "depart_time": "",
      "stay_min": ""
    }
  ],
  "fares": {
    "price_hard_seat": 163.5
  },
  "fetched_at": "2026-05-01T09:59:42.414350"
}