{
  "train_no": "K8138",
  "train_type": "K",
  "depart_station": "赤壁",
  "arrive_station": "漯河",
  "depart_time": "15:08",
  "arrive_time": "22:39",
  "stops": [
    {
      "seq": 1,
      "station_name": "赤壁",
      "arrive_time": "15:08",
      "depart_time": "15:08",
      "stay_min": ""
    },
    {
      "seq": 2,
      "station_name": "咸宁",
      "arrive_time": "15:36",
      "depart_time": "15:40",
      "stay_min": "4"
    },
    {
      "seq": 3,
      "station_name": "云梦",
      "arrive_time": "11:18",
      "depart_time": "11:22",
      "stay_min": "4"
    },
    {
      "seq": 4,
      "station_name": "武昌",
      "arrive_time": "16:47",
      "depart_time": "17:11",
      "stay_min": "24"
    },
    {
      "seq": 5,
      "station_name": "安陆",
      "arrive_time": "11:39",
      "depart_time": "11:49",
      "stay_min": "10"
    },
    {
      "seq": 6,
      "station_name": "孝感",
      "arrive_time": "18:16",
      "depart_time": "18:20",
      "stay_min": "4"
    },
    {
      "seq": 7,
      "station_name": "随州",
      "arrive_time": "12:25",
      "depart_time": "12:34",
      "stay_min": "9"
    },
    {
      "seq": 8,
      "station_name": "花园",
      "arrive_time": "18:41",
      "depart_time": "18:46",
      "stay_min": "5"
    },
    {
      "seq": 9,
      "station_name": "枣阳",
      "arrive_time": "13:24",
      "depart_time": "13:32",
      "stay_min": "8"
    },
    {
      "seq": 10,
      "station_name": "广水",
      "arrive_time": "19:17",
      "depart_time": "19:21",
      "stay_min": "4"
    },
    {
      "seq": 11,
      "station_name": "襄阳",
      "arrive_time": "14:15",
      "depart_time": "14:15",
      "stay_min": ""
    },
    {
      "seq": 12,
      "station_name": "信阳",
      "arrive_time": "20:10",
      "depart_time": "20:20",
      "stay_min": "10"
    },
    {
      "seq": 13,
      "station_name": "确山",
      "arrive_time": "21:10",
      "depart_time": "21:15",
      "stay_min": "5"
    },
    {
      "seq": 14,
      "station_name": "驻马店",
      "arrive_time": "21:29",
      "depart_time": "21:33",
      "stay_min": "4"
    },
    {
      "seq": 15,
      "station_name": "西平",
      "arrive_time": "22:07",
      "depart_time": "22:11",
      "stay_min": "4"
    },
    {
      "seq": 16,
      "station_name": "漯河",
      "arrive_time": "22:39",
      "depart_time": "",
      "stay_min": ""
    }
  ],
  "fares": {
    "price_hard_seat": 72.0
  },
  "fetched_at": "2026-05-01T10:36:22.085956"
}