{
  "train_no": "S8153",
  "train_type": "S",
  "depart_station": "海口",
  "arrive_station": "海口东",
  "depart_time": "12:54",
  "arrive_time": "13:15",
  "stops": [
    {
      "seq": 1,
      "station_name": "海口",
      "arrive_time": "12:54",
      "depart_time": "12:54",
      "stay_min": ""
    },
    {
      "seq": 2,
      "station_name": "长流",
      "arrive_time": "13:03",
      "depart_time": "13:03",
      "stay_min": ""
    },
    {
      "seq": 3,
      "station_name": "秀英",
      "arrive_time": "13:09",
      "depart_time": "13:09",
      "stay_min": ""
    },
    {
      "seq": 4,
      "station_name": "城西",
      "arrive_time": "13:15",
      "depart_time": "",
      "stay_min": ""
    },
    {
      "seq": 5,
      "station_name": "海口东",
      "arrive_time": "13:15",
      "depart_time": "",
      "stay_min": ""
    }
  ],
  "fares": {
    "price_second": 8.0,
    "price_no_seat": 8.0
  },
  "fetched_at": "2026-05-01T11:20:01.985593"
}