{
  "train_no": "Y901",
  "train_type": "Y",
  "depart_station": "库车",
  "arrive_station": "库尔勒",
  "depart_time": "19:30",
  "arrive_time": "09:48",
  "stops": [
    {
      "seq": 1,
      "station_name": "库车",
      "arrive_time": "19:30",
      "depart_time": "19:30",
      "stay_min": ""
    },
    {
      "seq": 2,
      "station_name": "贵阳",
      "arrive_time": "08:33",
      "depart_time": "08:33",
      "stay_min": ""
    },
    {
      "seq": 3,
      "station_name": "阿克苏",
      "arrive_time": "21:51",
      "depart_time": "22:00",
      "stay_min": "9"
    },
    {
      "seq": 4,
      "station_name": "凯里",
      "arrive_time": "10:49",
      "depart_time": "10:54",
      "stay_min": "5"
    },
    {
      "seq": 5,
      "station_name": "喀什",
      "arrive_time": "05:17",
      "depart_time": "05:17",
      "stay_min": ""
    },
    {
      "seq": 6,
      "station_name": "镇远",
      "arrive_time": "12:08",
      "depart_time": "12:08",
      "stay_min": ""
    },
    {
      "seq": 7,
      "station_name": "吐鲁番",
      "arrive_time": "04:50",
      "depart_time": "04:56",
      "stay_min": "6"
    },
    {
      "seq": 8,
      "station_name": "乌鲁木齐",
      "arrive_time": "06:47",
      "depart_time": "06:47",
      "stay_min": ""
    },
    {
      "seq": 9,
      "station_name": "吐鲁番",
      "arrive_time": "06:25",
      "depart_time": "06:31",
      "stay_min": "6"
    },
    {
      "seq": 10,
      "station_name": "库尔勒",
      "arrive_time": "09:48",
      "depart_time": "",
      "stay_min": ""
    }
  ],
  "fares": {},
  "fetched_at": "2026-05-01T11:41:08.043461"
}